galsim/catalog.py
galsim/gsparams.py
galsim/box.py
galsim/sensor.py
galsim/inclined.py
galsim/wfirst.py
galsim/fits.py
galsim/gsobject.py
galsim/knots.py
galsim/zernike.py
galsim/_galsim.cpython-313-darwin.so
galsim/_version.py
galsim/hsm.py
galsim/_pyfits.py
galsim/airy.py
galsim/sed.py
galsim/angle.py
galsim/convolve.py
galsim/deltafunction.py
galsim/galaxy_sample.py
galsim/integ.py
galsim/interpolatedimage.py
galsim/nfw_halo.py
galsim/second_kick.py
galsim/__init__.py
galsim/celestial.py
galsim/shear.py
galsim/real.py
galsim/exponential.py
galsim/lensing_ps.py
galsim/shapelet.py
galsim/random.py
galsim/phase_psf.py
galsim/_utilities.py
galsim/pse.py
galsim/wcs.py
galsim/chromatic.py
galsim/position.py
galsim/cdmodel.py
galsim/noise.py
galsim/transform.py
galsim/fouriersqrt.py
galsim/detectors.py
galsim/table.py
galsim/errors.py
galsim/download_cosmos.py
galsim/fft.py
galsim/sum.py
galsim/fitswcs.py
galsim/spergel.py
galsim/moffat.py
galsim/phase_screens.py
galsim/utilities.py
galsim/meta_data.py
galsim/vonkarman.py
galsim/main.py
galsim/bounds.py
galsim/sersic.py
galsim/photon_array.py
galsim/image.py
galsim/__main__.py
galsim/bessel.py
galsim/interpolant.py
galsim/gaussian.py
galsim/kolmogorov.py
galsim/correlatednoise.py
galsim/bandpass.py
galsim/dcr.py
galsim/des/des_shapelet.py
galsim/des/des_meds.py
galsim/des/__init__.py
galsim/des/des_psfex.py
galsim/config/image_scattered.py
galsim/config/extra_badpix.py
galsim/config/extra.py
galsim/config/sensor.py
galsim/config/gsobject.py
galsim/config/extra_truth.py
galsim/config/sed.py
galsim/config/util.py
galsim/config/input_real.py
galsim/config/value_random.py
galsim/config/stamp_ring.py
galsim/config/input_fitsheader.py
galsim/config/__init__.py
galsim/config/extra_weight.py
galsim/config/photon_ops.py
galsim/config/wcs.py
galsim/config/image_tiled.py
galsim/config/stamp.py
galsim/config/input.py
galsim/config/noise.py
galsim-2.8.3.dist-info/RECORD
galsim-2.8.3.dist-info/WHEEL
galsim-2.8.3.dist-info/entry_points.txt
galsim-2.8.3.dist-info/top_level.txt
galsim-2.8.3.dist-info/METADATA
galsim-2.8.3.dist-info/licenses/LICENSE
