Metadata-Version: 2.4
Name: GalSim
Version: 2.8.3
Summary: The modular galaxy image simulation toolkit
Home-page: https://github.com/GalSim-developers/GalSim
Download-URL: https://github.com/GalSim-developers/GalSim/releases/tag/v2.8.3.zip
Author: GalSim Developers (point of contact: Mike Jarvis)
Author-email: michael@jarvis.net
License: BSD License
License-File: LICENSE
Requires-Dist: setuptools>=38
Requires-Dist: pybind11>=2.2
Requires-Dist: numpy>=1.17
Requires-Dist: astropy
Requires-Dist: LSSTDESC.Coord
Dynamic: author
Dynamic: author-email
Dynamic: description
Dynamic: download-url
Dynamic: home-page
Dynamic: license
Dynamic: license-file
Dynamic: requires-dist
Dynamic: summary
